Metadata-Version: 2.1
Name: py3dgame
Version: 0.0.1
Home-page: https://github.com/Mattia-Vicari/py3dgame
Author: Vicarius
Author-email: 
Project-URL: Bug Reports, https://github.com/Mattia-Vicari/py3dgame/issues
Classifier: Development Status :: 1 - Planning
Classifier: License :: OSI Approved :: MIT License
Classifier: Programming Language :: Python :: 3
Requires-Python: >= 3.10
Requires-Dist: numpy
Requires-Dist: pygame
